mldft/.env
mldft/__init__.py
mldft/api/cli_ofdft.py
mldft/api/instantiate_from_args.py
mldft/api/setup.py
mldft/datagen/__init__.py
mldft/datagen/datasets/QMUGSLargeBins_Ids.txt
mldft/datagen/datasets/__init__.py
mldft/datagen/datasets/dataset.py
mldft/datagen/datasets/misc.py
mldft/datagen/datasets/qm9.py
mldft/datagen/datasets/qmugs.py
mldft/datagen/datasets/small_dataset.py
mldft/datagen/datasets/two_electron_dataset.py
mldft/datagen/generate_labels_dataset.py
mldft/datagen/kohn_sham_dataset.py
mldft/datagen/methods/__init__.py
mldft/datagen/methods/density_fitting.py
mldft/datagen/methods/ksdft_calculation.py
mldft/datagen/methods/label_generation.py
mldft/datagen/methods/save_labels_in_zarr_file.py
mldft/datagen/transform_dataset.py
mldft/ml/__init__.py
mldft/ml/callbacks/__init__.py
mldft/ml/callbacks/base.py
mldft/ml/callbacks/checkpoint.py
mldft/ml/callbacks/custom_scalars.py
mldft/ml/callbacks/image_logging.py
mldft/ml/callbacks/log_gradient_norm.py
mldft/ml/callbacks/mesh_logging.py
mldft/ml/callbacks/print_overrides_callback.py
mldft/ml/callbacks/sub_model_summary.py
mldft/ml/callbacks/timing.py
mldft/ml/compute_dataset_statistics.py
mldft/ml/data/__init__.py
mldft/ml/data/components/__init__.py
mldft/ml/data/components/basis_info.py
mldft/ml/data/components/basis_transforms.py
mldft/ml/data/components/convert_transforms.py
mldft/ml/data/components/dataset.py
mldft/ml/data/components/loader.py
mldft/ml/data/components/of_batch.py
mldft/ml/data/components/of_data.py
mldft/ml/data/datamodule.py
mldft/ml/models/__init__.py
mldft/ml/models/components/__init__.py
mldft/ml/models/components/atom_ref.py
mldft/ml/models/components/density_coeff_embedding.py
mldft/ml/models/components/dimension_wise_rescaling.py
mldft/ml/models/components/g3d_layer.py
mldft/ml/models/components/g3d_layer_tf.py
mldft/ml/models/components/g3d_stack.py
mldft/ml/models/components/gbf_module.py
mldft/ml/models/components/graphformer.py
mldft-0.0.1.dist-info/WHEEL
mldft-0.0.1.dist-info/entry_points.txt
mldft-0.0.1.dist-info/METADATA
mldft-0.0.1.dist-info/RECORD
