Metadata-Version: 2.3
Name: mldft
Version: 0.0.1
Summary: OF-DFT using machine learning
Author: Scientific AI (Hamprecht Lab, Heidelberg University)
Requires-Dist: scikit-learn
Requires-Dist: geometric
Requires-Dist: zarr==2.18.4
Requires-Dist: numcodecs==0.15
Requires-Dist: pyscf==2.4.0
Requires-Dist: notebook
Requires-Dist: hydra-core>=1.0.0,<2.0.0
Requires-Dist: numpy
Requires-Dist: rdkit
Requires-Dist: polars
Requires-Dist: rich>=13.0.0,<14.0.0
Requires-Dist: h5py
Requires-Dist: tensorboard
Requires-Dist: hydra-optuna-sweeper
Requires-Dist: hydra-colorlog
Requires-Dist: rootutils
Requires-Dist: loguru
Requires-Dist: opt-einsum
Requires-Dist: tqdm
Requires-Dist: gpustat
Requires-Dist: ase>=3.19
Requires-Dist: sphinx
Requires-Dist: sphinx-rtd-theme
Requires-Dist: pyvista[all]
Requires-Dist: basis-set-exchange
Requires-Dist: pypdf
Requires-Dist: gitpython
Requires-Dist: seaborn
Requires-Dist: lmdb
Requires-Dist: torch==2.4.1
Requires-Dist: torchvision==0.19.1
Requires-Dist: torchaudio==2.4.1
Requires-Dist: lightning==2.5.0
Requires-Dist: torch-geometric==2.6.1
Requires-Dist: e3nn
Requires-Dist: torchmetrics>=0.0.0,<1.0.0
Requires-Dist: huggingface-hub==0.*
Requires-Python: >=3.11, <3.13
Project-URL: homepage, https://github.com/sciai-lab/structures25
